robot_hat/__init__.py
robot_hat/exceptions.py
robot_hat/filedb.py
robot_hat/music.py
robot_hat/pin.py
robot_hat/utils.py
robot_hat/version.py
robot_hat/common/__init__.py
robot_hat/common/event_emitter.py
robot_hat/common/singleton_meta.py
robot_hat/data_types/__init__.py
robot_hat/data_types/bus.py
robot_hat/data_types/config/__init__.py
robot_hat/data_types/config/battery.py
robot_hat/data_types/config/ina219.py
robot_hat/data_types/config/ina226.py
robot_hat/data_types/config/ina260.py
robot_hat/data_types/config/motor.py
robot_hat/data_types/config/pwm.py
robot_hat/data_types/config/sh3001.py
robot_hat/drivers/__init__.py
robot_hat/drivers/adc/INA219.py
robot_hat/drivers/adc/INA226.py
robot_hat/drivers/adc/INA260.py
robot_hat/drivers/adc/__init__.py
robot_hat/drivers/adc/sunfounder_adc.py
robot_hat/drivers/pwm/__init__.py
robot_hat/drivers/pwm/pca9685.py
robot_hat/drivers/pwm/sunfounder_pwm.py
robot_hat/factories/__init__.py
robot_hat/factories/battery_factory.py
robot_hat/factories/motor_factory.py
robot_hat/factories/pwm_factory.py
robot_hat/i2c/__init__.py
robot_hat/i2c/i2c_bus.py
robot_hat/i2c/i2c_manager.py
robot_hat/i2c/retry_decorator.py
robot_hat/i2c/smbus_manager.py
robot_hat/i2c/smbus_protocol.py
robot_hat/interfaces/__init__.py
robot_hat/interfaces/battery_abc.py
robot_hat/interfaces/imu_abc.py
robot_hat/interfaces/motor_abc.py
robot_hat/interfaces/pwm_driver_abc.py
robot_hat/interfaces/servo_abc.py
robot_hat/interfaces/smbus_abc.py
robot_hat/mock/__init__.py
robot_hat/mock/smbus2.py
robot_hat/mock/ultrasonic.py
robot_hat/motor/__init__.py
robot_hat/motor/gpio_dc_motor.py
robot_hat/motor/i2c_dc_motor.py
robot_hat/motor/phase_motor.py
robot_hat/motor/mixins/__init__.py
robot_hat/motor/mixins/motor_calibration.py
robot_hat/sensors/__init__.py
robot_hat/sensors/imu/__init__.py
robot_hat/sensors/imu/sh3001.py
robot_hat/sensors/ultrasonic/HC_SR04.py
robot_hat/sensors/ultrasonic/__init__.py
robot_hat/services/__init__.py
robot_hat/services/motor_service.py
robot_hat-2.2.1.dist-info/licenses/LICENSE
robot_hat-2.2.1.dist-info/METADATA
robot_hat-2.2.1.dist-info/WHEEL
robot_hat-2.2.1.dist-info/top_level.txt
robot_hat-2.2.1.dist-info/RECORD
