Metadata-Version: 2.4
Name: robot_hat
Version: 2.2.1
Summary: Extensible and type-hinted library for controlling robot hardware (motors, servos, ultrasonic, ADC, I2C).
Author-email: Karim Aziiev <karim.aziiev@gmail.com>
License-Expression: GPL-3.0-or-later
Keywords: i2c,raspberrypi
License-File: LICENSE
Requires-Dist: pygame
Requires-Dist: smbus2
Requires-Dist: gpiozero
Requires-Dist: RPi.GPIO
Requires-Dist: tenacity
Provides-Extra: dev
Requires-Dist: black; extra == "dev"
Requires-Dist: isort; extra == "dev"
Requires-Dist: pre-commit; extra == "dev"
Dynamic: license-file
